{
    "version": "20131101",
    "logo": "http://image.aladin.co.kr/img/header/2011/aladin_logo_new.gif",
    "title": "알라딘 신간 에세이",
    "link": "https:\/\/www.aladin.co.kr\/shop\/common\/wbest.aspx?BestType=Bestseller&amp;BranchType=1&amp;CID=55890&amp;Year=2021&amp;Month=5&amp;Week=2&amp;partner=openAPI",
    "pubDate": "Tue, 11 May 2021 05:58:31 GMT",
    "totalResults": 1000,
    "startIndex": 1,
    "itemsPerPage": 30,
    "query": "QueryType=BESTSELLER;CategoryId=55890;Year=2021;Month=5;Week=2",
    "searchCategoryId": 55890,
    "searchCategoryName": "전체",
    "item": [
        {
            "title": "길 떠나는 설레임",
            "link": "http:\/\/www.aladin.co.kr\/shop\/wproduct.aspx?ItemId=271217383&amp;partner=openAPI&amp;start=api",
            "author": "조성민 (지은이)",
            "pubDate": "2021-05-03",
            "description": "도서정보를 준비중입니다.",
            "isbn": "K692731140",
            "isbn13": "9791197420207",
            "itemId": 271217383,
            "priceSales": 11400,
            "priceStandard": 12000,
            "mallType": "BOOK",
            "stockStatus": "",
            "mileage": 600,
            "cover": "https:\/\/image.aladin.co.kr\/product\/27121\/73\/cover150\/k692731140_1.jpg",
            "categoryId": 51371,
            "categoryName": "국내도서>에세이>한국에세이",
            "publisher": "신비",
            "salesPoint": 0,
            "adult": false,
            "fixedPrice": true,
            "customerReviewRank": 7,
            "subInfo": {}
        },
        {
            "title": "희망한 적 없는 희망퇴직 - 내 이야기가 될 줄은 몰랐던 희망퇴직 이야기",
            "link": "http:\/\/www.aladin.co.kr\/shop\/wproduct.aspx?ItemId=271218295&amp;partner=openAPI&amp;start=api",
            "author": "이래하 (지은이), 최해성 (사진)",
            "pubDate": "2021-05-19",
            "description": "일자리는 곧 생존의 문제다. 일자리를 구하는 사람들은 아무렇게나 대해도 되는 자들이 아니라, 마땅히 사람답게 존중받아야 할 자들이다. 일자리를 둘러싼 생존과 존엄성을 두고 저자는 우리가 걸어나가야 할 방향을 제시하고 있다.",
            "isbn": "K992731141",
            "isbn13": "9791189930912",
            "itemId": 271218295,
            "priceSales": 13500,
            "priceStandard": 15000,
            "mallType": "BOOK",
            "stockStatus": "예약판매",
            "mileage": 750,
            "cover": "https:\/\/image.aladin.co.kr\/product\/27121\/82\/cover150\/k992731141_1.jpg",
            "categoryId": 2944,
            "categoryName": "국내도서>자기계발>취업\/진로\/유망직업>국내 진학\/취업",
            "publisher": "하모니북",
            "salesPoint": 0,
            "adult": false,
            "fixedPrice": true,
            "customerReviewRank": 8,
            "subInfo": {}
        },
        {
            "title": "나의 아름다운 세상 나들이",
            "link": "http:\/\/www.aladin.co.kr\/shop\/wproduct.aspx?ItemId=271218791&amp;partner=openAPI&amp;start=api",
            "author": "문호일 (지은이)",
            "pubDate": "2021-04-19",
            "description": "도서정보를 준비중입니다.",
            "isbn": "K192731141",
            "isbn13": "9791137242937",
            "itemId": 271218791,
            "priceSales": 13200,
            "priceStandard": 13200,
            "mallType": "BOOK",
            "stockStatus": "",
            "mileage": 0,
            "cover": "https:\/\/image.aladin.co.kr\/product\/27121\/87\/cover150\/k192731141_1.jpg",
            "categoryId": 51371,
            "categoryName": "국내도서>에세이>한국에세이",
            "publisher": "부크크(bookk)",
            "salesPoint": 0,
            "adult": false,
            "fixedPrice": true,
            "customerReviewRank": 6,
            "subInfo": {}
        },
        {
            "title": "그냥하고싶었던말",
            "link": "http:\/\/www.aladin.co.kr\/shop\/wproduct.aspx?ItemId=271218930&amp;partner=openAPI&amp;start=api",
            "author": "박수현 (지은이)",
            "pubDate": "2021-04-12",
            "description": "도서정보를 준비중입니다.",
            "isbn": "K252731141",
            "isbn13": "9791137240452",
            "itemId": 271218930,
            "priceSales": 12400,
            "priceStandard": 12400,
            "mallType": "BOOK",
            "stockStatus": "",
            "mileage": 0,
            "cover": "https:\/\/image.aladin.co.kr\/product\/27121\/89\/cover150\/k252731141_1.jpg",
            "categoryId": 51371,
            "categoryName": "국내도서>에세이>한국에세이",
            "publisher": "부크크(bookk)",
            "salesPoint": 0,
            "adult": false,
            "fixedPrice": true,
            "customerReviewRank": 7,
            "subInfo": {}
        },
        {
            "title": "이만하면 괜찮은 남자는 없다 - 왜 평범해 보이는 남성도 여성 혐오에 빠지는가",
            "link": "http:\/\/www.aladin.co.kr\/shop\/wproduct.aspx?ItemId=271221206&amp;partner=openAPI&amp;start=api",
            "author": "박정훈 (지은이)",
            "pubDate": "2021-05-10",
            "description": "첫 책 《친절하게 웃어주면 결혼까지 생각하는 남자들》에서 남성 문화를 비판하고 반성의 목소리를 냈던 〈오마이뉴스〉 박정훈 기자가 이번 책에서는 한 발 더 나아가 여성혐오·성폭력·착취의 근원이 남성들의 ‘기만’에 있다는 것을 논지한다.",
            "isbn": "K322731142",
            "isbn13": "9791160404777",
            "itemId": 271221206,
            "priceSales": 13500,
            "priceStandard": 15000,
            "mallType": "BOOK",
            "stockStatus": "",
            "mileage": 750,
            "cover": "https:\/\/image.aladin.co.kr\/product\/27122\/12\/cover150\/k322731142_1.jpg",
            "categoryId": 51326,
            "categoryName": "국내도서>사회과학>여성학\/젠더>여성문제",
            "publisher": "한겨레출판",
            "salesPoint": 1710,
            "adult": false,
            "fixedPrice": true,
            "customerReviewRank": 8,
            "subInfo": {}
        },
        {
            "title": "허리춤을 내준 시카고 남자",
            "link": "http:\/\/www.aladin.co.kr\/shop\/wproduct.aspx?ItemId=271224039&amp;partner=openAPI&amp;start=api",
            "author": "차은숙 (지은이)",
            "pubDate": "2021-05-12",
            "description": "저자는 수없이 많은 만남과 이별을 통해 새로운 자신을 발견하고 삶의 지혜를 얻는다. 여행은 낯선 사람들과의 만남이며 그 만남은 또 다른 인연으로 이어져 한 사람의 인생을 장식한다. 두려움을 안고 떠난 유학길에서, 설렘으로 가득한 배낭여행지에서 시행착오를 겪으면서 자아를 발견한다.",
            "isbn": "K272731143",
            "isbn13": "9791191697001",
            "itemId": 271224039,
            "priceSales": 12600,
            "priceStandard": 14000,
            "mallType": "BOOK",
            "stockStatus": "",
            "mileage": 700,
            "cover": "https:\/\/image.aladin.co.kr\/product\/27122\/40\/cover150\/k272731143_1.jpg",
            "categoryId": 51371,
            "categoryName": "국내도서>에세이>한국에세이",
            "publisher": "소울앤북",
            "salesPoint": 0,
            "adult": false,
            "fixedPrice": true,
            "customerReviewRank": 6,
            "subInfo": {}
        },
        {
            "title": "엄마! 엄마! - 엄마를 위한 작은 책",
            "link": "http:\/\/www.aladin.co.kr\/shop\/wproduct.aspx?ItemId=271233101&amp;partner=openAPI&amp;start=api",
            "author": "리즈 클라이모 (지은이), 정영임 (옮긴이)",
            "pubDate": "2021-05-08",
            "description": "사랑스러운 동물 만화 &lt;리즈 클라이모의 작은 세상&gt;으로 전 세계 독자들에게 큰 사랑을 받은 리즈 클라이모가 엄마를 위한 작은 책을 만들었다. 엄마들이 마주하는 어려운 사정과 충만한 사랑의 시간을 재치 있고 매력 넘치는 동물 그림으로 담아낸 그림책이다.",
            "isbn": "K572731144",
            "isbn13": "9791165880972",
            "itemId": 271233101,
            "priceSales": 13500,
            "priceStandard": 15000,
            "mallType": "BOOK",
            "stockStatus": "",
            "mileage": 750,
            "cover": "https:\/\/image.aladin.co.kr\/product\/27123\/31\/cover150\/k572731144_1.jpg",
            "categoryId": 51376,
            "categoryName": "국내도서>에세이>사진\/그림 에세이",
            "publisher": "북극곰",
            "salesPoint": 110,
            "adult": false,
            "fixedPrice": true,
            "customerReviewRank": 4,
            "subInfo": {}
        },
        {
            "title": "꽃이 내게로 와!",
            "link": "http:\/\/www.aladin.co.kr\/shop\/wproduct.aspx?ItemId=271234044&amp;partner=openAPI&amp;start=api",
            "author": "여여 (지은이)",
            "pubDate": "2021-04-26",
            "description": "숲 속에 핀 한 송이 작은 은방울꽃에 귀를 기울여보라. 맑고 푸른 새벽 종소리, 말하지 않는 생물들의 재잘거림, 부처님의 사자후와 우주의 기침 소리도 함께 들릴 것이다. 한 송이 꽃이 우주요 자연이며 진리를 품은 비밀의 책이다. 스쳐 지나가지 말고 잘 읽어볼 일이다.",
            "isbn": "8967451229",
            "isbn13": "9788967451226",
            "itemId": 271234044,
            "priceSales": 16200,
            "priceStandard": 18000,
            "mallType": "BOOK",
            "stockStatus": "",
            "mileage": 900,
            "cover": "https:\/\/image.aladin.co.kr\/product\/27123\/40\/cover150\/8967451229_1.jpg",
            "categoryId": 51376,
            "categoryName": "국내도서>에세이>사진\/그림 에세이",
            "publisher": "이른아침",
            "salesPoint": 0,
            "adult": false,
            "fixedPrice": true,
            "customerReviewRank": 6,
            "subInfo": {}
        },
        {
            "title": "행복의 모양은 삼각형",
            "link": "http:\/\/www.aladin.co.kr\/shop\/wproduct.aspx?ItemId=271234206&amp;partner=openAPI&amp;start=api",
            "author": "양주연 (지은이)",
            "pubDate": "2021-05-14",
            "description": "등산극혐주의자에서 등산애호가가 된 30대 직장인의 본격 ‘산으로 가는’ 이야기다. 한때 꼰대들의 전유물로 여겨졌던 등산은 밀레니얼 세대에게 힙하고 트렌디한 운동이 되었다. 빌딩 숲에서, 짜증나게 하는 사람들 틈에서 벗어나 조용히 혼자만의 시간을 갖고 싶을 때 밀레니얼 세대는 산으로 떠난다.",
            "isbn": "8972979899",
            "isbn13": "9788972979890",
            "itemId": 271234206,
            "priceSales": 11700,
            "priceStandard": 13000,
            "mallType": "BOOK",
            "stockStatus": "",
            "mileage": 650,
            "cover": "https:\/\/image.aladin.co.kr\/product\/27123\/42\/cover150\/8972979899_1.jpg",
            "categoryId": 51371,
            "categoryName": "국내도서>에세이>한국에세이",
            "publisher": "디귿",
            "salesPoint": 0,
            "adult": false,
            "fixedPrice": true,
            "customerReviewRank": 2,
            "subInfo": {}
        },
        {
            "title": "눈으로 말하니 만상이 보이네",
            "link": "http:\/\/www.aladin.co.kr\/shop\/wproduct.aspx?ItemId=271236945&amp;partner=openAPI&amp;start=api",
            "author": "이제길 (지은이)",
            "pubDate": "2021-04-30",
            "description": "도서정보를 준비중입니다.",
            "isbn": "K182731145",
            "isbn13": "9791159333347",
            "itemId": 271236945,
            "priceSales": 11700,
            "priceStandard": 13000,
            "mallType": "BOOK",
            "stockStatus": "",
            "mileage": 650,
            "cover": "https:\/\/image.aladin.co.kr\/product\/27123\/69\/cover150\/k182731145_1.jpg",
            "categoryId": 51371,
            "categoryName": "국내도서>에세이>한국에세이",
            "publisher": "수필과비평사",
            "salesPoint": 0,
            "adult": false,
            "fixedPrice": true,
            "customerReviewRank": 3,
            "subInfo": {}
        },
        {
            "title": "고도를 살다",
            "link": "http:\/\/www.aladin.co.kr\/shop\/wproduct.aspx?ItemId=271237160&amp;partner=openAPI&amp;start=api",
            "author": "김은옥 (지은이)",
            "pubDate": "2021-05-05",
            "description": "도서정보를 준비중입니다.",
            "isbn": "K192731145",
            "isbn13": "9791159333361",
            "itemId": 271237160,
            "priceSales": 11700,
            "priceStandard": 13000,
            "mallType": "BOOK",
            "stockStatus": "",
            "mileage": 650,
            "cover": "https:\/\/image.aladin.co.kr\/img\/noimg_150_b.jpg",
            "categoryId": 51371,
            "categoryName": "국내도서>에세이>한국에세이",
            "publisher": "수필과비평사",
            "salesPoint": 0,
            "adult": false,
            "fixedPrice": true,
            "customerReviewRank": 4,
            "subInfo": {}
        },
        {
            "title": "어쩌다, 승무원 - 서비스와 안전 사이, 아슬했던 비행의 기록들",
            "link": "http:\/\/www.aladin.co.kr\/shop\/wproduct.aspx?ItemId=271238244&amp;partner=openAPI&amp;start=api",
            "author": "김연실 (지은이)",
            "pubDate": "2021-05-15",
            "description": "’똘끼‘ 충만한 전직 승무원이 들려주는 생생하고 솔직한 리얼 비행 스토리. 저자의 값지고 진솔한 경험들이 이 책을 통해 조금이나마 전달되길 바라며, 승무원에 대한 궁금증과 여행 시 팁이 될 만한 정보도 함께 넣어 비행기에 탑승할 때 누구에게나 도움이 될 수 있도록 했다.",
            "isbn": "K362731145",
            "isbn13": "9791197072918",
            "itemId": 271238244,
            "priceSales": 12600,
            "priceStandard": 14000,
            "mallType": "BOOK",
            "stockStatus": "",
            "mileage": 700,
            "cover": "https:\/\/image.aladin.co.kr\/product\/27123\/82\/cover150\/k362731145_1.jpg",
            "categoryId": 51376,
            "categoryName": "국내도서>에세이>사진\/그림 에세이",
            "publisher": "언제나북스",
            "salesPoint": 110,
            "adult": false,
            "fixedPrice": true,
            "customerReviewRank": 6,
            "subInfo": {}
        },
        {
            "title": "쪽은 팔릴수록 좋다 - 사람 마음을 움직이는 사람",
            "link": "http:\/\/www.aladin.co.kr\/shop\/wproduct.aspx?ItemId=271241043&amp;partner=openAPI&amp;start=api",
            "author": "황의중 (지은이)",
            "pubDate": "2021-05-17",
            "description": "퇴직한 국어선생님이 현역 시절 제자들에게 직접 써 나눠준 글들을 모아 묶은 책 「쪽은 팔릴수록 좋다」가 출간됐다. 황의중 선생님이 제자들에게 글을 쓴 이유는 단순했다. 제자들에게 도움이 될 만한 이야기들을 ‘교실에서 말로 떠드는 것보다 글로 써서 나눠주면 더 낫지 않을까?’라는 소소한 고민이었다.",
            "isbn": "K562731145",
            "isbn13": "9791185253862",
            "itemId": 271241043,
            "priceSales": 18000,
            "priceStandard": 20000,
            "mallType": "BOOK",
            "stockStatus": "",
            "mileage": 1000,
            "cover": "https:\/\/image.aladin.co.kr\/product\/27124\/10\/cover150\/k562731145_1.jpg",
            "categoryId": 51371,
            "categoryName": "국내도서>에세이>한국에세이",
            "publisher": "민중의소리",
            "salesPoint": 110,
            "adult": false,
            "fixedPrice": true,
            "customerReviewRank": 8,
            "subInfo": {}
        },
        {
            "title": "윤상원 일기 - 님을 위한 행진곡의 주인공, 시민군 대변인",
            "link": "http:\/\/www.aladin.co.kr\/shop\/wproduct.aspx?ItemId=271242278&amp;partner=openAPI&amp;start=api",
            "author": "윤상원 (지은이), 황광우 (엮은이)",
            "pubDate": "2021-05-18",
            "description": "1980년 5월 27일 광주항쟁 당시 마지막까지 도청을 지켰던 윤상원의 일기다. 윤상원은 1960년부터 1979년까지 열권의 일기를 썼다. 1980년 5월 20일, 그는 밤새워 투사회보를 작성하였고 27일 새벽 4시까지 도청을 사수하였다.",
            "isbn": "K632731145",
            "isbn13": "9791197378638",
            "itemId": 271242278,
            "priceSales": 45000,
            "priceStandard": 50000,
            "mallType": "BOOK",
            "stockStatus": "",
            "mileage": 2500,
            "cover": "https:\/\/image.aladin.co.kr\/product\/27124\/22\/cover150\/k632731145_1.jpg",
            "categoryId": 51402,
            "categoryName": "국내도서>에세이>일기\/편지",
            "publisher": "(주)글통",
            "salesPoint": 0,
            "adult": false,
            "fixedPrice": true,
            "customerReviewRank": 7,
            "subInfo": {}
        },
        {
            "title": "윤석동 일기 - 역사의 제단에 아들을 바친, 윤상원의 아버지",
            "link": "http:\/\/www.aladin.co.kr\/shop\/wproduct.aspx?ItemId=271242707&amp;partner=openAPI&amp;start=api",
            "author": "윤석동 (지은이), 황광우 (엮은이)",
            "pubDate": "2021-05-18",
            "description": "80년대를 살아온 우리는 모두들 한번쯤 고민해본 질문이 있었다. “80년 광주의 그 날, 내가 윤상원이었다면 정말 죽을 줄 알면서도 그 자리를 지킬 수 있었을까?” 이 책은 1980년 5월 27일 광주항쟁 당시 마지막까지 도청을 지켰던 윤상원의 아버지 윤석동의 일기다.",
            "isbn": "K772731145",
            "isbn13": "9791197378645",
            "itemId": 271242707,
            "priceSales": 45000,
            "priceStandard": 50000,
            "mallType": "BOOK",
            "stockStatus": "",
            "mileage": 2500,
            "cover": "https:\/\/image.aladin.co.kr\/product\/27124\/27\/cover150\/k772731145_1.jpg",
            "categoryId": 51402,
            "categoryName": "국내도서>에세이>일기\/편지",
            "publisher": "(주)글통",
            "salesPoint": 0,
            "adult": false,
            "fixedPrice": true,
            "customerReviewRank": 6,
            "subInfo": {}
        },
        {
            "title": "영감은 어떻게 시가 되는가",
            "link": "http:\/\/www.aladin.co.kr\/shop\/wproduct.aspx?ItemId=271257896&amp;partner=openAPI&amp;start=api",
            "author": "윤창영 (지은이)",
            "pubDate": "2021-04-13",
            "description": "도서정보를 준비중입니다.",
            "isbn": "K762731146",
            "isbn13": "9791137242371",
            "itemId": 271257896,
            "priceSales": 12200,
            "priceStandard": 12200,
            "mallType": "BOOK",
            "stockStatus": "",
            "mileage": 0,
            "cover": "https:\/\/image.aladin.co.kr\/product\/27125\/78\/cover150\/k762731146_1.jpg",
            "categoryId": 51371,
            "categoryName": "국내도서>에세이>한국에세이",
            "publisher": "부크크(bookk)",
            "salesPoint": 110,
            "adult": false,
            "fixedPrice": true,
            "customerReviewRank": 3,
            "subInfo": {}
        },
        {
            "title": "오덕후 평전",
            "link": "http:\/\/www.aladin.co.kr\/shop\/wproduct.aspx?ItemId=271258018&amp;partner=openAPI&amp;start=api",
            "author": "병풍이 (지은이)",
            "pubDate": "2021-04-12",
            "description": "도서정보를 준비중입니다.",
            "isbn": "K792731146",
            "isbn13": "9791137242340",
            "itemId": 271258018,
            "priceSales": 7000,
            "priceStandard": 7000,
            "mallType": "BOOK",
            "stockStatus": "",
            "mileage": 0,
            "cover": "https:\/\/image.aladin.co.kr\/product\/27125\/80\/cover150\/k792731146_1.jpg",
            "categoryId": 51371,
            "categoryName": "국내도서>에세이>한국에세이",
            "publisher": "부크크(bookk)",
            "salesPoint": 0,
            "adult": false,
            "fixedPrice": true,
            "customerReviewRank": 2,
            "subInfo": {}
        },
        {
            "title": "더 크라잉 북 - 지극한 슬픔, 은밀한 눈물에 관하여",
            "link": "http:\/\/www.aladin.co.kr\/shop\/wproduct.aspx?ItemId=259678355&amp;partner=openAPI&amp;start=api",
            "author": "헤더 크리스털 (지은이), 오윤성 (옮긴이)",
            "pubDate": "2021-05-17",
            "description": "시인인 헤더 크리스털은 아름답고 감동적인 에세이 『더 크라잉 북』에서 인간이 하는 가장 인간적인 행위, 울음에 대해 탐구한다. 저자는 눈물의 생물학적 원인을 설명하고, 울음이 예술과 정치, 페미니즘, 인종, 문화에 끼치는 영향을 조사하는 동시에, 사랑하는 친구의 자살, 가족력으로 내려오는 우울증, 임신에 이르기까지 자신의 눈물에 깃든 내밀한 이야기를 들려준다.",
            "isbn": "K572731149",
            "isbn13": "9791189799472",
            "itemId": 259678355,
            "priceSales": 15120,
            "priceStandard": 16800,
            "mallType": "BOOK",
            "stockStatus": "",
            "mileage": 840,
            "cover": "https:\/\/image.aladin.co.kr\/product\/25967\/83\/cover150\/k572731149_2.jpg",
            "categoryId": 51373,
            "categoryName": "국내도서>에세이>외국에세이",
            "publisher": "북트리거",
            "salesPoint": 110,
            "adult": false,
            "fixedPrice": true,
            "customerReviewRank": 8,
            "subInfo": {}
        },
        {
            "title": "아픔은 당신 탓이 아닙니다 (큰글씨책) - 환자의 뒷모습을 보며 속으로 주워 삼킨 이야기들",
            "link": "http:\/\/www.aladin.co.kr\/shop\/wproduct.aspx?ItemId=271056879&amp;partner=openAPI&amp;start=api",
            "author": "김대현, 류현철, 장석창 (지은이)",
            "pubDate": "2021-05-20",
            "description": "의사들의 마음속에는 결코 작지 않은 공간이 있다. 환자와의 시간이 고스란히 기억된 공간이다. 그 기억을 잊지 않기 위해, 그래서 다음 환자에게 더 나은 의료를 제공하기 위해 의사들은 펜을 든다. 환자와의 시간을 통해 경험했던 특별한 이야기, 환자와 주고받았던 가슴 울리는 대화들, 그리고 그들에게 차마 못다 한 속마음이 솔직하게 적힌 42편의 이야기가 실렸다.",
            "isbn": "8991232930",
            "isbn13": "9788991232938",
            "itemId": 271056879,
            "priceSales": 31000,
            "priceStandard": 31000,
            "mallType": "BOOK",
            "stockStatus": "",
            "mileage": 930,
            "cover": "https:\/\/image.aladin.co.kr\/product\/27105\/68\/cover150\/8991232930_1.jpg",
            "categoryId": 51371,
            "categoryName": "국내도서>에세이>한국에세이",
            "publisher": "청년의사",
            "salesPoint": 0,
            "adult": false,
            "fixedPrice": true,
            "customerReviewRank": 10,
            "subInfo": {}
        },
        {
            "title": "쓸수록 나는 내가 된다 - 텅 빈 마음을 어루만지는 성찰과 치유의 글쓰기",
            "link": "http:\/\/www.aladin.co.kr\/shop\/wproduct.aspx?ItemId=271008684&amp;partner=openAPI&amp;start=api",
            "author": "손화신 (지은이)",
            "pubDate": "2021-05-10",
            "description": "일반인 작가의 데뷔를 돕는, 꿈의 등용문이 된 브런치에서 2회나 수상한 손화신 작가는 자신이 왜 글을 쓰는지, 글쓰기란 무엇인지를 부단히 성찰했고, 이런 성찰의 중요성을 각종 글쓰기 강연을 통해 글을 쓰고 싶어 하는 사람을 만나면서 전하고 있다.",
            "isbn": "K842731040",
            "isbn13": "9791130637402",
            "itemId": 271008684,
            "priceSales": 12600,
            "priceStandard": 14000,
            "mallType": "BOOK",
            "stockStatus": "예약판매",
            "mileage": 700,
            "cover": "https:\/\/image.aladin.co.kr\/product\/27100\/86\/cover150\/k842731040_1.jpg",
            "categoryId": 51538,
            "categoryName": "국내도서>인문학>책읽기\/글쓰기>글쓰기",
            "publisher": "다산초당(다산북스)",
            "salesPoint": 210,
            "adult": false,
            "fixedPrice": true,
            "customerReviewRank": 10,
            "subInfo": {}
        }

    ]
}